fastauth/__init__.py
fastauth/csrf.py
fastauth/dependencies.py
fastauth/middleware.py
fastauth/models.py
fastauth/storage.py
fastauth/tasks.py
fastauth/token.py
fast_guardian-0.1.0.dist-info/LICENSE
fast_guardian-0.1.0.dist-info/METADATA
fast_guardian-0.1.0.dist-info/WHEEL
fast_guardian-0.1.0.dist-info/RECORD
