Metadata-Version: 2.3
Name: fast-guardian
Version: 0.1.0
Summary: Authentication middleware for FastAPI with JWT and role-based access control
Author: Your Name
Author-email: your.email@example.com
Requires-Python: >=3.12,<4.0
Classifier: Programming Language :: Python :: 3
Classifier: Programming Language :: Python :: 3.12
Classifier: Programming Language :: Python :: 3.13
Requires-Dist: fastapi (>=0.104.0,<0.105.0)
Requires-Dist: passlib[bcrypt] (>=1.7.4,<2.0.0)
Requires-Dist: pydantic (>=2.4,<3.0)
Requires-Dist: python-jose[cryptography] (>=3.3.0,<4.0.0)
Requires-Dist: python-multipart (>=0.0.6,<0.0.7)
Requires-Dist: redis (>=5.2.1,<6.0.0)
